xraydawgz/Core.py
xraydawgz/Predict.py
xraydawgz/__init__.py
xraydawgz/version.py
xraydawgz/tests/__init__.py
xraydawgz/tests/core.py
xraydawgz/tests/core_test.py
xraydawgz-0.2.dist-info/LICENSE
xraydawgz-0.2.dist-info/METADATA
xraydawgz-0.2.dist-info/WHEEL
xraydawgz-0.2.dist-info/top_level.txt
xraydawgz-0.2.dist-info/RECORD
